<?xml version="1.0" encoding="utf-8"?>
<deployment>
  <id>94f9b8a0ce5c48eabd4a63983909e016</id>
  <author>N/A</author>
  <deployer>OneDeploy</deployer>
  <authorEmail>N/A</authorEmail>
  <message>OneDeploy</message>
  <progress></progress>
  <status>Success</status>
  <statusText></statusText>
  <lastSuccessEndTime>2025-10-13T17:23:16.8909059Z</lastSuccessEndTime>
  <receivedTime>2025-10-13T17:22:51.547385Z</receivedTime>
  <startTime>2025-10-13T17:22:52.0683968Z</startTime>
  <endTime>2025-10-13T17:23:16.8909059Z</endTime>
  <complete>True</complete>
  <is_temp>False</is_temp>
  <is_readonly>True</is_readonly>
  <project_type>OneDeploy</project_type>
  <vsproject_id></vsproject_id>
</deployment>